rebiber/__init__.py
rebiber/_version.py
rebiber/bib2json.py
rebiber/bib_list.txt
rebiber/example_input.bib
rebiber/example_output.bib
rebiber/normalize.py
rebiber/data/aaai2010.bib.json
rebiber/data/aaai2011.bib.json
rebiber/data/aaai2012.bib.json
rebiber/data/aaai2013.bib.json
rebiber/data/aaai2014.bib.json
rebiber/data/aaai2015.bib.json
rebiber/data/aaai2015.json
rebiber/data/aaai2016.bib.json
rebiber/data/aaai2017.json
rebiber/data/aaai2018-2.bib.json
rebiber/data/aaai2018.bib.json
rebiber/data/aaai2019.json
rebiber/data/aaai2020.json
rebiber/data/acl.json
rebiber/data/aistats2013.bib.json
rebiber/data/aistats2014.bib.json
rebiber/data/aistats2015.bib.json
rebiber/data/aistats2016.bib.json
rebiber/data/aistats2017.bib.json
rebiber/data/aistats2018.bib.json
rebiber/data/aistats2019.bib.json
rebiber/data/aistats2020.bib.json
rebiber/data/aistats2021.bib.json
rebiber/data/alenex2010.bib.json
rebiber/data/alenex2011.bib.json
rebiber/data/alenex2012.bib.json
rebiber/data/alenex2013.bib.json
rebiber/data/alenex2014.bib.json
rebiber/data/alenex2015.bib.json
rebiber/data/alenex2016.bib.json
rebiber/data/alenex2017.bib.json
rebiber/data/alenex2018.bib.json
rebiber/data/alenex2019.bib.json
rebiber/data/alenex2020.bib.json
rebiber/data/asonam2010.bib.json
rebiber/data/asonam2011.bib.json
rebiber/data/asonam2012.bib.json
rebiber/data/asonam2013.bib.json
rebiber/data/asonam2014.bib.json
rebiber/data/asonam2015.bib.json
rebiber/data/asonam2016.bib.json
rebiber/data/asonam2017.bib.json
rebiber/data/asonam2018.bib.json
rebiber/data/asonam2019.bib.json
rebiber/data/bigdataconf2013.bib.json
rebiber/data/bigdataconf2014.bib.json
rebiber/data/bigdataconf2015.bib.json
rebiber/data/bigdataconf2016.bib.json
rebiber/data/bigdataconf2017.bib.json
rebiber/data/bigdataconf2018.bib.json
rebiber/data/bigdataconf2019.bib.json
rebiber/data/bmvc2010.bib.json
rebiber/data/bmvc2011.bib.json
rebiber/data/bmvc2012.bib.json
rebiber/data/bmvc2013.bib.json
rebiber/data/bmvc2014.bib.json
rebiber-1.1.3.dist-info/LICENSE
rebiber-1.1.3.dist-info/METADATA
rebiber-1.1.3.dist-info/WHEEL
rebiber-1.1.3.dist-info/entry_points.txt
rebiber-1.1.3.dist-info/top_level.txt
rebiber-1.1.3.dist-info/RECORD
