Metadata-Version: 2.1
Name: rebiber
Version: 1.1.3
Summary: A tool for normalizing bibtex with official info.
Home-page: https://github.com/yuchenlin/rebiber
Author: Bill Yuchen Lin and Yang Qiao
Author-email: yuchen.lin@usc.edu
License: UNKNOWN
Platform: UNKNOWN
Classifier: Programming Language :: Python :: 3
Classifier: License :: OSI Approved :: MIT License
Classifier: Operating System :: OS Independent
Requires-Python: >=3.6
Requires-Dist: argparse
Requires-Dist: bibtexparser
Requires-Dist: tqdm
